Assignment2/majority.v
`timescale 1ns/100ps

module majority(
    input a,
    input b,
    input c,
    output reg x);
  
  always @ * 
    case ({a,b,c})
      3'b000 : x = 0;
      3'b001 : x = 0;
      3'b010 : x = 0;
      3'b011 : x = 1;
      3'b100 : x = 0;
      3'b101 : x = 1;
      3'b110 : x = 1;
      3'b111 : x = 1;
    endcase
endmodule

Assignment2/testbench.v
`timescale 1ns/100ps

module majority_TB();
  reg in1, in2, in3, in4, in5;
  wire my_out, my_z;
  
  //pullup(my_z);
  //pulldown(my_z);
  
  majority trend(
    .a(in1),
    .b(in2),
    .c(in3),
    .x(my_out)
  );
  
  initial
    begin
      $dumpfile("dump.vcd"); 
      $dumpvars(1,majority_TB,my_z);
      {in1,in2,in3}=3'b000;
      #10;
      {in1,in2,in3}=3'b001;
      #10;
      {in1,in2,in3}=3'b010;
      #10;
      {in1,in2,in3}=3'b011;
      #10;
      {in1,in2,in3}=3'b100;
      #10;
      {in1,in2,in3}=3'b101;
      #10; 
      {in1,in2,in3}=3'b110;
      #10; 
      {in1,in2,in3}=3'b111;
      #10; 
      $finish;
    end
endmodule

Assignment2/dump.vcd
$date
	Thu Oct 17 17:21:19 2024
$end
$version
	ModelSim Version 10.5b
$end
$timescale
	100ps
$end

$scope module majority_TB $end
$var reg 1 ! in1 $end
$var reg 1 " in2 $end
$var reg 1 # in3 $end
$var reg 1 $ in4 $end
$var reg 1 % in5 $end
$var wire 1 & my_out $end
$var wire 1 ' my_z $end
$var wire 1 ' my_z $end
$upscope $end
$enddefinitions $end
#0
$dumpvars
0!
0"
0#
x$
x%
0&
z'
$end
#100
1#
#200
0#
1"
#300
1#
1&
#400
0#
0"
1!
0&
#500
1#
1&
#600
0#
1"
#700
1#
