Assignment1/majority.v
`timescale 1ns/100ps

//////////////////////////////////////////////////////////////////////////////////
// Company: Closure Labs
// Engineer: Eduardo Corpeño
// 
// Create Date:    Feb-23-2018 
// Module Name:    majority
// Description:    A simple 3-input majority function implemented with gates.
//
// Revision: 1.0
// Revision 0.01 - File Created
// Additional Comments: Part of the FPGA Embedded Design course by Closure Labs.
//
//////////////////////////////////////////////////////////////////////////////////

module majority(
    input a,
    input b,
    input c,
    output x);
  
  wire b_c, and_out, bc;
  
  and (and_out,a,b_c);
  and (bc,c,b);
  or  (b_c,b,c);
  or  (x,and_out,bc);
endmodule

Assignment1/testbench.v
`timescale 1ns/100ps

//////////////////////////////////////////////////////////////////////////////////
// Company: Closure Labs
// Engineer: Eduardo Corpeño
// 
// Create Date:    Feb-23-2018 
// Module Name:    majority_TB
// Description:    Testbench for a simple 3-input majority function implemented with gates.
//
// Revision: 1.0
// Revision 0.01 - File Created
// Additional Comments: Part of the FPGA Embedded Design course by Closure Labs.
//                      This example features the pullup and pulldown primitives.
//
//////////////////////////////////////////////////////////////////////////////////

module majority_TB();
  reg in1, in2, in3, in4, in5;
  wire my_out, my_z;
  
  pullup(my_z);
  //pulldown(my_z);
  
  majority trend(
    .a(in1),
    .b(in2),
    .c(in3),
    .x(my_out)
  );
  
  initial
    begin
      $dumpfile("dump.vcd"); 
      $dumpvars(1,majority_TB,my_z);
      {in1,in2,in3}=3'b000;
      #10;
      {in1,in2,in3}=3'b001;
      #10;
      {in1,in2,in3}=3'b010;
      #10;
      {in1,in2,in3}=3'b011;
      #10;
      {in1,in2,in3}=3'b100;
      #10;
      {in1,in2,in3}=3'b101;
      #10;
      {in1,in2,in3}=3'b110;
      #10;
      {in1,in2,in3}=3'b111;
      #10;
      $finish;
    end
endmodule

Assignment1/dump.vcd
$date
	Thu Oct 10 19:58:54 2024
$end
$version
	ModelSim Version 10.5b
$end
$timescale
	100ps
$end

$scope module majority_TB $end
$var reg 1 ! in1 $end
$var reg 1 " in2 $end
$var reg 1 # in3 $end
$var reg 1 $ in4 $end
$var reg 1 % in5 $end
$var wire 1 & my_out $end
$var wire 1 ' my_z $end
$var wire 1 ' my_z $end
$upscope $end
$enddefinitions $end
#0
$dumpvars
0!
0"
0#
x$
x%
0&
1'
$end
#100
1#
#200
0#
1"
#300
1#
1&
#400
0#
0"
1!
0&
#500
1#
1&
#600
0#
1"
#700
1#
