four_one_mux/four_to_one_mux.v
`timescale 1ns/100ps

module four_to_one_mux(
  input [3:0] my_ins,
  input [1:0] sel,
  output my_out
  );
  
  assign my_out = 
    (~sel[1] & ~sel[0] & my_ins[0]) |
    (~sel[1] &  sel[0] & my_ins[1]) |
    ( sel[1] & ~sel[0] & my_ins[2]) |
    ( sel[1] &  sel[0] & my_ins[3]);
endmodule

four_one_mux/testbench.v
`timescale 1ns/100ps

module mux_TB();
  reg in0, in1, in2, in3;
  reg [1:0] select;
  wire out;
  
  four_to_one_mux my_mux({in3,in2,in1,in0},select,out);
  always #0.1 in0=~in0;
  always #0.5 in1=~in1;
  always #1 in2=~in2;
  always #5 in3=~in3;
  
  initial begin
    $dumpfile("out.vcd");
    $dumpvars(1,mux_TB);
    in0=0;
    in1=0;
    in2=0;
    in3=0;
    select=2'b00;
    #20
    select=2'b01;
    #20
    select=2'b10;
    #20
    select=2'b11;
    #20
    $finish;
  end

endmodule

four_one_mux/out.vcd
$date
	Thu Oct 17 21:58:45 2024
$end
$version
	ModelSim Version 10.5b
$end
$timescale
	100ps
$end

$scope module mux_TB $end
$var reg 1 ! in0 $end
$var reg 1 " in1 $end
$var reg 1 # in2 $end
$var reg 1 $ in3 $end
$var reg 2 % select [1:0] $end
$var wire 1 & out $end
$upscope $end
$enddefinitions $end
#0
$dumpvars
0!
0"
0#
0$
b0 %
0&
$end
#1
1!
1&
#2
0!
0&
#3
1!
1&
#4
0!
0&
#5
1"
1!
1&
#6
0!
0&
#7
1!
1&
#8
0!
0&
#9
1!
1&
#10
1#
0"
0!
0&
#11
1!
1&
#12
0!
0&
#13
1!
1&
#14
0!
0&
#15
1"
1!
1&
#16
0!
0&
#17
1!
1&
#18
0!
0&
#19
1!
1&
#20
0#
0"
0!
0&
#21
1!
1&
#22
0!
0&
#23
1!
1&
#24
0!
0&
#25
1"
1!
1&
#26
0!
0&
#27
1!
1&
#28
0!
0&
#29
1!
1&
#30
1#
0"
0!
0&
#31
1!
1&
#32
0!
0&
#33
1!
1&
#34
0!
0&
#35
1"
1!
1&
#36
0!
0&
#37
1!
1&
#38
0!
0&
#39
1!
1&
#40
0#
0"
0!
0&
#41
1!
1&
#42
0!
0&
#43
1!
1&
#44
0!
0&
#45
1"
1!
1&
#46
0!
0&
#47
1!
1&
#48
0!
0&
#49
1!
1&
#50
1$
1#
0"
0!
0&
#51
1!
1&
#52
0!
0&
#53
1!
1&
#54
0!
0&
#55
1"
1!
1&
#56
0!
0&
#57
1!
1&
#58
0!
0&
#59
1!
1&
#60
0#
0"
0!
0&
#61
1!
1&
#62
0!
0&
#63
1!
1&
#64
0!
0&
#65
1"
1!
1&
#66
0!
0&
#67
1!
1&
#68
0!
0&
#69
1!
1&
#70
1#
0"
0!
0&
#71
1!
1&
#72
0!
0&
#73
1!
1&
#74
0!
0&
#75
1"
1!
1&
#76
0!
0&
#77
1!
1&
#78
0!
0&
#79
1!
1&
#80
0#
0"
0!
0&
#81
1!
1&
#82
0!
0&
#83
1!
1&
#84
0!
0&
#85
1"
1!
1&
#86
0!
0&
#87
1!
1&
#88
0!
0&
#89
1!
1&
#90
1#
0"
0!
0&
#91
1!
1&
#92
0!
0&
#93
1!
1&
#94
0!
0&
#95
1"
1!
1&
#96
0!
0&
#97
1!
1&
#98
0!
0&
#99
1!
1&
#100
0$
0#
0"
0!
0&
#101
1!
1&
#102
0!
0&
#103
1!
1&
#104
0!
0&
#105
1"
1!
1&
#106
0!
0&
#107
1!
1&
#108
0!
0&
#109
1!
1&
#110
1#
0"
0!
0&
#111
1!
1&
#112
0!
0&
#113
1!
1&
#114
0!
0&
#115
1"
1!
1&
#116
0!
0&
#117
1!
1&
#118
0!
0&
#119
1!
1&
#120
0#
0"
0!
0&
#121
1!
1&
#122
0!
0&
#123
1!
1&
#124
0!
0&
#125
1"
1!
1&
#126
0!
0&
#127
1!
1&
#128
0!
0&
#129
1!
1&
#130
1#
0"
0!
0&
#131
1!
1&
#132
0!
0&
#133
1!
1&
#134
0!
0&
#135
1"
1!
1&
#136
0!
0&
#137
1!
1&
#138
0!
0&
#139
1!
1&
#140
0#
0"
0!
0&
#141
1!
1&
#142
0!
0&
#143
1!
1&
#144
0!
0&
#145
1"
1!
1&
#146
0!
0&
#147
1!
1&
#148
0!
0&
#149
1!
1&
#150
1$
1#
0"
0!
0&
#151
1!
1&
#152
0!
0&
#153
1!
1&
#154
0!
0&
#155
1"
1!
1&
#156
0!
0&
#157
1!
1&
#158
0!
0&
#159
1!
1&
#160
0#
0"
0!
0&
#161
1!
1&
#162
0!
0&
#163
1!
1&
#164
0!
0&
#165
1"
1!
1&
#166
0!
0&
#167
1!
1&
#168
0!
0&
#169
1!
1&
#170
1#
0"
0!
0&
#171
1!
1&
#172
0!
0&
#173
1!
1&
#174
0!
0&
#175
1"
1!
1&
#176
0!
0&
#177
1!
1&
#178
0!
0&
#179
1!
1&
#180
0#
0"
0!
0&
#181
1!
1&
#182
0!
0&
#183
1!
1&
#184
0!
0&
#185
1"
1!
1&
#186
0!
0&
#187
1!
1&
#188
0!
0&
#189
1!
1&
#190
1#
0"
0!
0&
#191
1!
1&
#192
0!
0&
#193
1!
1&
#194
0!
0&
#195
1"
1!
1&
#196
0!
0&
#197
1!
1&
#198
0!
0&
#199
1!
1&
#200
b1 %
0$
0#
0"
0!
0&
#201
1!
#202
0!
#203
1!
#204
0!
#205
1"
1!
1&
#206
0!
#207
1!
#208
0!
#209
1!
#210
1#
0"
0!
0&
#211
1!
#212
0!
#213
1!
#214
0!
#215
1"
1!
1&
#216
0!
#217
1!
#218
0!
#219
1!
#220
0#
0"
0!
0&
#221
1!
#222
0!
#223
1!
#224
0!
#225
1"
1!
1&
#226
0!
#227
1!
#228
0!
#229
1!
#230
1#
0"
0!
0&
#231
1!
#232
0!
#233
1!
#234
0!
#235
1"
1!
1&
#236
0!
#237
1!
#238
0!
#239
1!
#240
0#
0"
0!
0&
#241
1!
#242
0!
#243
1!
#244
0!
#245
1"
1!
1&
#246
0!
#247
1!
#248
0!
#249
1!
#250
1$
1#
0"
0!
0&
#251
1!
#252
0!
#253
1!
#254
0!
#255
1"
1!
1&
#256
0!
#257
1!
#258
0!
#259
1!
#260
0#
0"
0!
0&
#261
1!
#262
0!
#263
1!
#264
0!
#265
1"
1!
1&
#266
0!
#267
1!
#268
0!
#269
1!
#270
1#
0"
0!
0&
#271
1!
#272
0!
#273
1!
#274
0!
#275
1"
1!
1&
#276
0!
#277
1!
#278
0!
#279
1!
#280
0#
0"
0!
0&
#281
1!
#282
0!
#283
1!
#284
0!
#285
1"
1!
1&
#286
0!
#287
1!
#288
0!
#289
1!
#290
1#
0"
0!
0&
#291
1!
#292
0!
#293
1!
#294
0!
#295
1"
1!
1&
#296
0!
#297
1!
#298
0!
#299
1!
#300
0$
0#
0"
0!
0&
#301
1!
#302
0!
#303
1!
#304
0!
#305
1"
1!
1&
#306
0!
#307
1!
#308
0!
#309
1!
#310
1#
0"
0!
0&
#311
1!
#312
0!
#313
1!
#314
0!
#315
1"
1!
1&
#316
0!
#317
1!
#318
0!
#319
1!
#320
0#
0"
0!
0&
#321
1!
#322
0!
#323
1!
#324
0!
#325
1"
1!
1&
#326
0!
#327
1!
#328
0!
#329
1!
#330
1#
0"
0!
0&
#331
1!
#332
0!
#333
1!
#334
0!
#335
1"
1!
1&
#336
0!
#337
1!
#338
0!
#339
1!
#340
0#
0"
0!
0&
#341
1!
#342
0!
#343
1!
#344
0!
#345
1"
1!
1&
#346
0!
#347
1!
#348
0!
#349
1!
#350
1$
1#
0"
0!
0&
#351
1!
#352
0!
#353
1!
#354
0!
#355
1"
1!
1&
#356
0!
#357
1!
#358
0!
#359
1!
#360
0#
0"
0!
0&
#361
1!
#362
0!
#363
1!
#364
0!
#365
1"
1!
1&
#366
0!
#367
1!
#368
0!
#369
1!
#370
1#
0"
0!
0&
#371
1!
#372
0!
#373
1!
#374
0!
#375
1"
1!
1&
#376
0!
#377
1!
#378
0!
#379
1!
#380
0#
0"
0!
0&
#381
1!
#382
0!
#383
1!
#384
0!
#385
1"
1!
1&
#386
0!
#387
1!
#388
0!
#389
1!
#390
1#
0"
0!
0&
#391
1!
#392
0!
#393
1!
#394
0!
#395
1"
1!
1&
#396
0!
#397
1!
#398
0!
#399
1!
#400
b10 %
0$
0#
0"
0!
0&
#401
1!
#402
0!
#403
1!
#404
0!
#405
1"
1!
#406
0!
#407
1!
#408
0!
#409
1!
#410
1#
0"
0!
1&
#411
1!
#412
0!
#413
1!
#414
0!
#415
1"
1!
#416
0!
#417
1!
#418
0!
#419
1!
#420
0#
0"
0!
0&
#421
1!
#422
0!
#423
1!
#424
0!
#425
1"
1!
#426
0!
#427
1!
#428
0!
#429
1!
#430
1#
0"
0!
1&
#431
1!
#432
0!
#433
1!
#434
0!
#435
1"
1!
#436
0!
#437
1!
#438
0!
#439
1!
#440
0#
0"
0!
0&
#441
1!
#442
0!
#443
1!
#444
0!
#445
1"
1!
#446
0!
#447
1!
#448
0!
#449
1!
#450
1$
1#
0"
0!
1&
#451
1!
#452
0!
#453
1!
#454
0!
#455
1"
1!
#456
0!
#457
1!
#458
0!
#459
1!
#460
0#
0"
0!
0&
#461
1!
#462
0!
#463
1!
#464
0!
#465
1"
1!
#466
0!
#467
1!
#468
0!
#469
1!
#470
1#
0"
0!
1&
#471
1!
#472
0!
#473
1!
#474
0!
#475
1"
1!
#476
0!
#477
1!
#478
0!
#479
1!
#480
0#
0"
0!
0&
#481
1!
#482
0!
#483
1!
#484
0!
#485
1"
1!
#486
0!
#487
1!
#488
0!
#489
1!
#490
1#
0"
0!
1&
#491
1!
#492
0!
#493
1!
#494
0!
#495
1"
1!
#496
0!
#497
1!
#498
0!
#499
1!
#500
0$
0#
0"
0!
0&
#501
1!
#502
0!
#503
1!
#504
0!
#505
1"
1!
#506
0!
#507
1!
#508
0!
#509
1!
#510
1#
0"
0!
1&
#511
1!
#512
0!
#513
1!
#514
0!
#515
1"
1!
#516
0!
#517
1!
#518
0!
#519
1!
#520
0#
0"
0!
0&
#521
1!
#522
0!
#523
1!
#524
0!
#525
1"
1!
#526
0!
#527
1!
#528
0!
#529
1!
#530
1#
0"
0!
1&
#531
1!
#532
0!
#533
1!
#534
0!
#535
1"
1!
#536
0!
#537
1!
#538
0!
#539
1!
#540
0#
0"
0!
0&
#541
1!
#542
0!
#543
1!
#544
0!
#545
1"
1!
#546
0!
#547
1!
#548
0!
#549
1!
#550
1$
1#
0"
0!
1&
#551
1!
#552
0!
#553
1!
#554
0!
#555
1"
1!
#556
0!
#557
1!
#558
0!
#559
1!
#560
0#
0"
0!
0&
#561
1!
#562
0!
#563
1!
#564
0!
#565
1"
1!
#566
0!
#567
1!
#568
0!
#569
1!
#570
1#
0"
0!
1&
#571
1!
#572
0!
#573
1!
#574
0!
#575
1"
1!
#576
0!
#577
1!
#578
0!
#579
1!
#580
0#
0"
0!
0&
#581
1!
#582
0!
#583
1!
#584
0!
#585
1"
1!
#586
0!
#587
1!
#588
0!
#589
1!
#590
1#
0"
0!
1&
#591
1!
#592
0!
#593
1!
#594
0!
#595
1"
1!
#596
0!
#597
1!
#598
0!
#599
1!
#600
b11 %
0$
0#
0"
0!
0&
#601
1!
#602
0!
#603
1!
#604
0!
#605
1"
1!
#606
0!
#607
1!
#608
0!
#609
1!
#610
1#
0"
0!
#611
1!
#612
0!
#613
1!
#614
0!
#615
1"
1!
#616
0!
#617
1!
#618
0!
#619
1!
#620
0#
0"
0!
#621
1!
#622
0!
#623
1!
#624
0!
#625
1"
1!
#626
0!
#627
1!
#628
0!
#629
1!
#630
1#
0"
0!
#631
1!
#632
0!
#633
1!
#634
0!
#635
1"
1!
#636
0!
#637
1!
#638
0!
#639
1!
#640
0#
0"
0!
#641
1!
#642
0!
#643
1!
#644
0!
#645
1"
1!
#646
0!
#647
1!
#648
0!
#649
1!
#650
1$
1#
0"
0!
1&
#651
1!
#652
0!
#653
1!
#654
0!
#655
1"
1!
#656
0!
#657
1!
#658
0!
#659
1!
#660
0#
0"
0!
#661
1!
#662
0!
#663
1!
#664
0!
#665
1"
1!
#666
0!
#667
1!
#668
0!
#669
1!
#670
1#
0"
0!
#671
1!
#672
0!
#673
1!
#674
0!
#675
1"
1!
#676
0!
#677
1!
#678
0!
#679
1!
#680
0#
0"
0!
#681
1!
#682
0!
#683
1!
#684
0!
#685
1"
1!
#686
0!
#687
1!
#688
0!
#689
1!
#690
1#
0"
0!
#691
1!
#692
0!
#693
1!
#694
0!
#695
1"
1!
#696
0!
#697
1!
#698
0!
#699
1!
#700
0$
0#
0"
0!
0&
#701
1!
#702
0!
#703
1!
#704
0!
#705
1"
1!
#706
0!
#707
1!
#708
0!
#709
1!
#710
1#
0"
0!
#711
1!
#712
0!
#713
1!
#714
0!
#715
1"
1!
#716
0!
#717
1!
#718
0!
#719
1!
#720
0#
0"
0!
#721
1!
#722
0!
#723
1!
#724
0!
#725
1"
1!
#726
0!
#727
1!
#728
0!
#729
1!
#730
1#
0"
0!
#731
1!
#732
0!
#733
1!
#734
0!
#735
1"
1!
#736
0!
#737
1!
#738
0!
#739
1!
#740
0#
0"
0!
#741
1!
#742
0!
#743
1!
#744
0!
#745
1"
1!
#746
0!
#747
1!
#748
0!
#749
1!
#750
1$
1#
0"
0!
1&
#751
1!
#752
0!
#753
1!
#754
0!
#755
1"
1!
#756
0!
#757
1!
#758
0!
#759
1!
#760
0#
0"
0!
#761
1!
#762
0!
#763
1!
#764
0!
#765
1"
1!
#766
0!
#767
1!
#768
0!
#769
1!
#770
1#
0"
0!
#771
1!
#772
0!
#773
1!
#774
0!
#775
1"
1!
#776
0!
#777
1!
#778
0!
#779
1!
#780
0#
0"
0!
#781
1!
#782
0!
#783
1!
#784
0!
#785
1"
1!
#786
0!
#787
1!
#788
0!
#789
1!
#790
1#
0"
0!
#791
1!
#792
0!
#793
1!
#794
0!
#795
1"
1!
#796
0!
#797
1!
#798
0!
#799
1!
