four_inp_demux/four_in_demux.v
`timescale 1ns/100ps


module four_in_demux(
  output reg [3:0] my_outs,
  input [1:0] sel,
  input my_in
  );
  parameter INACTIVE = 0;
  always @ * begin
    if(sel==2'b00) begin
      my_outs[0]=my_in;
      my_outs[1]=INACTIVE;
      my_outs[2]=INACTIVE;
      my_outs[3]=INACTIVE;
    end
    else
      if(sel==2'b01)begin
        my_outs[0]=INACTIVE;
        my_outs[1]=my_in;
        my_outs[2]=INACTIVE;
        my_outs[3]=INACTIVE;
      end
      else
        if(sel==2'b10)begin
          my_outs[0]=INACTIVE;
          my_outs[1]=INACTIVE;
          my_outs[2]=my_in;
          my_outs[3]=INACTIVE;
        end
        else begin
          my_outs[0]=INACTIVE;
          my_outs[1]=INACTIVE;
          my_outs[2]=INACTIVE;
          my_outs[3]=my_in;
        end

  end
  
endmodule

four_inp_demux/testbench.v
`timescale 1ns/100ps

module demux_TB();
  reg in;
  reg [1:0] select;
  wire out0, out1, out2, out3;
  
  four_in_demux my_demux({out3,out2,out1,out0},select,in);
  always #1 in=~in;
  
  initial begin
    $dumpfile("out.vcd");
    $dumpvars(1,demux_TB);
    in=0;
    select=2'b00;
    #20
    select=2'b01;
    #20
    select=2'b10;
    #20
    select=2'b11;
    #20
    $finish;
  end

endmodule

four_inp_demux/out.vcd
$date
	Thu Oct 17 17:49:24 2024
$end
$version
	ModelSim Version 10.5b
$end
$timescale
	100ps
$end

$scope module demux_TB $end
$var reg 1 ! in $end
$var reg 2 " select [1:0] $end
$var wire 1 # out0 $end
$var wire 1 $ out1 $end
$var wire 1 % out2 $end
$var wire 1 & out3 $end
$upscope $end
$enddefinitions $end
#0
$dumpvars
0!
b0 "
0#
0$
0%
0&
$end
#10
1!
1#
#20
0!
0#
#30
1!
1#
#40
0!
0#
#50
1!
1#
#60
0!
0#
#70
1!
1#
#80
0!
0#
#90
1!
1#
#100
0!
0#
#110
1!
1#
#120
0!
0#
#130
1!
1#
#140
0!
0#
#150
1!
1#
#160
0!
0#
#170
1!
1#
#180
0!
0#
#190
1!
1#
#200
b1 "
0!
0#
#210
1!
1$
#220
0!
0$
#230
1!
1$
#240
0!
0$
#250
1!
1$
#260
0!
0$
#270
1!
1$
#280
0!
0$
#290
1!
1$
#300
0!
0$
#310
1!
1$
#320
0!
0$
#330
1!
1$
#340
0!
0$
#350
1!
1$
#360
0!
0$
#370
1!
1$
#380
0!
0$
#390
1!
1$
#400
b10 "
0!
0$
#410
1!
1%
#420
0!
0%
#430
1!
1%
#440
0!
0%
#450
1!
1%
#460
0!
0%
#470
1!
1%
#480
0!
0%
#490
1!
1%
#500
0!
0%
#510
1!
1%
#520
0!
0%
#530
1!
1%
#540
0!
0%
#550
1!
1%
#560
0!
0%
#570
1!
1%
#580
0!
0%
#590
1!
1%
#600
b11 "
0!
0%
#610
1!
1&
#620
0!
0&
#630
1!
1&
#640
0!
0&
#650
1!
1&
#660
0!
0&
#670
1!
1&
#680
0!
0&
#690
1!
1&
#700
0!
0&
#710
1!
1&
#720
0!
0&
#730
1!
1&
#740
0!
0&
#750
1!
1&
#760
0!
0&
#770
1!
1&
#780
0!
0&
#790
1!
1&
